flask_appfactory/__init__.py
flask_appfactory/app.py
flask_appfactory/celery.py
flask_appfactory/cli.py
flask_appfactory/version.py
flask_appfactory/ext/__init__.py
flask_appfactory/ext/jinja2.py
Flask_AppFactory-0.2.1.dist-info/top_level.txt
Flask_AppFactory-0.2.1.dist-info/METADATA
Flask_AppFactory-0.2.1.dist-info/DESCRIPTION.rst
Flask_AppFactory-0.2.1.dist-info/metadata.json
Flask_AppFactory-0.2.1.dist-info/WHEEL
Flask_AppFactory-0.2.1.dist-info/RECORD
