Metadata-Version: 2.0
Name: Flask-AppFactory
Version: 0.2.1
Summary: Flask-AppFactory is an dynamic application loader.
Home-page: http://github.com/inveniosoftware/flask-appfactory/
Author: Invenio Collaboration
Author-email: info@invenio-software.org
License: BSD
Platform: any
Classifier: Programming Language :: Python :: 2
Classifier: Programming Language :: Python :: 2.6
Classifier: Programming Language :: Python :: 2.7
Classifier: Programming Language :: Python :: 3
Classifier: Programming Language :: Python :: 3.3
Classifier: Programming Language :: Python :: 3.4
Classifier: Environment :: Web Environment
Classifier: Development Status :: 5 - Production/Stable
Classifier: Intended Audience :: Developers
Classifier: License :: OSI Approved :: BSD License
Classifier: Operating System :: OS Independent
Classifier: Topic :: Utilities
Requires-Dist: Flask (>=0.10)
Requires-Dist: Flask-Registry (>=0.2.0)
Requires-Dist: Flask-CLI (>=0.2.1)
Provides-Extra: celery
Requires-Dist: Flask-CeleryExt (>=0.1.0); extra == 'celery'
